soundofgothic/__init__.py
soundofgothic/Dialogs/__init__.py
oundofgothic-0.1.dist-info/METADATA
oundofgothic-0.1.dist-info/WHEEL
oundofgothic-0.1.dist-info/top_level.txt
oundofgothic-0.1.dist-info/RECORD
