Metadata-Version: 2.1
Name: oundofgothic
Version: 0.1
Summary: SoundOfGothic.pl Python API wrapper.
Home-page: https://github.com/kubinka0505/oundofgothic
Author: kubinka0505
License: GPL V3
Keywords: gothic oundofgothic sog python api api-wrapper
Platform: UNKNOWN
Classifier: Development Status :: 4 - Beta
Classifier: Environment :: Console
Classifier: Intended Audience :: End Users/Desktop
Classifier: License :: OSI Approved :: GNU General Public License v3 (GPLv3)
Classifier: Natural Language :: English
Classifier: Programming Language :: Python :: 3 :: Only
Classifier: Topic :: Multimedia :: Sound/Audio
